pytest_testrail/__init__.py
pytest_testrail/conftest.py
pytest_testrail/plugin.py
pytest_testrail/testrail_api.py
pytest_testrail-3.1.1.dist-info/METADATA
pytest_testrail-3.1.1.dist-info/WHEEL
pytest_testrail-3.1.1.dist-info/entry_points.txt
pytest_testrail-3.1.1.dist-info/licenses/LICENSE
pytest_testrail-3.1.1.dist-info/RECORD
