Metadata-Version: 2.4
Name: pytest-testrail
Version: 3.1.1
Summary: A pytest plugin for creating TestRail runs and adding results
Project-URL: Homepage, https://github.com/allankp/pytest-testrail
Project-URL: Repository, https://github.com/allankp/pytest-testrail
Project-URL: Documentation, https://github.com/allankp/pytest-testrail#readme
Project-URL: Issues, https://github.com/allankp/pytest-testrail/issues
Project-URL: Changelog, https://github.com/allankp/pytest-testrail/releases
Author-email: Allan Kilpatrick <allanklp@gmail.com>
License-Expression: MIT
License-File: LICENSE
Keywords: pytest,qa,test-management,testing,testrail
Classifier: Development Status :: 5 - Production/Stable
Classifier: Framework :: Pytest
Classifier: Intended Audience :: Developers
Classifier: License :: OSI Approved :: MIT License
Classifier: Operating System :: OS Independent
Classifier: Programming Language :: Python :: 3
Classifier: Programming Language :: Python :: 3.10
Classifier: Programming Language :: Python :: 3.11
Classifier: Programming Language :: Python :: 3.12
Classifier: Programming Language :: Python :: 3.13
Classifier: Topic :: Software Development :: Quality Assurance
Classifier: Topic :: Software Development :: Testing
Classifier: Typing :: Typed
Requires-Python: >=3.10
Requires-Dist: pytest>=7.0.0
Requires-Dist: requests>=2.28.0
